certbot_dns_contabo/__init__.py
certbot_dns_contabo/dns_contabo.py
certbot_dns_contabo_api-1.0.2.dist-info/METADATA
certbot_dns_contabo_api-1.0.2.dist-info/WHEEL
certbot_dns_contabo_api-1.0.2.dist-info/entry_points.txt
certbot_dns_contabo_api-1.0.2.dist-info/top_level.txt
certbot_dns_contabo_api-1.0.2.dist-info/RECORD
